dask_labextension_gateway.py
dask_labextension_gateway-0.1.0.data/data/etc/jupyter/jupyter_server_config.d/dask_labextension_gateway.json
dask_labextension_gateway-0.1.0.dist-info/LICENSE
dask_labextension_gateway-0.1.0.dist-info/METADATA
dask_labextension_gateway-0.1.0.dist-info/WHEEL
dask_labextension_gateway-0.1.0.dist-info/top_level.txt
dask_labextension_gateway-0.1.0.dist-info/RECORD
