Metadata-Version: 2.2
Name: dask-labextension-gateway
Version: 0.1.0
Summary: Add Dask Gateway support to dask-labextension
Author-email: Min RK <benjaminrk@gmail.com>
License: BSD-3-Clause
Project-URL: Homepage, https://github.com/minrk/dask-labextension-gateway
Project-URL: Source, https://github.com/minrk/dask-labextension-gateway
Project-URL: Tracker, https://github.com/minrk/dask-labextension-gateway/issues
Keywords: Dask,Jupyter
Classifier: Development Status :: 1 - Planning
Classifier: Intended Audience :: Developers
Classifier: Intended Audience :: System Administrators
Classifier: Intended Audience :: Science/Research
Classifier: License :: OSI Approved :: BSD License
Classifier: Programming Language :: Python
Classifier: Programming Language :: Python :: 3
Classifier: Framework :: Jupyter
Requires-Python: >=3.9
License-File: LICENSE
Requires-Dist: dask-gateway
Requires-Dist: dask-labextension
Provides-Extra: test
Requires-Dist: dask-gateway-server[local]; extra == "test"
Requires-Dist: pytest; extra == "test"
Requires-Dist: pytest-asyncio; extra == "test"
Requires-Dist: pytest-cov; extra == "test"
